drfseriperm/__init__.py
drfseriperm/ffp.py
drfseriperm/missing.py
drfseriperm/mixins.py
drfseriperm/renderers.py
drfseriperm-1.1.3.dist-info/licenses/LICENSE
drfseriperm-1.1.3.dist-info/METADATA
drfseriperm-1.1.3.dist-info/WHEEL
drfseriperm-1.1.3.dist-info/top_level.txt
drfseriperm-1.1.3.dist-info/RECORD
