Metadata-Version: 2.4
Name: drfseriperm
Version: 1.1.3
Author: DouleLove
License: MIT License
Project-URL: Repository, https://github.com/DouleLove/drfseriperm
Project-URL: Issues, https://github.com/DouleLove/drfkwargs/drfseriperm
Classifier: Development Status :: 4 - Beta
Classifier: Intended Audience :: Developers
Classifier: Topic :: Utilities
Classifier: Natural Language :: English
Classifier: Operating System :: OS Independent
Classifier: License :: OSI Approved :: MIT License
Classifier: Programming Language :: Python :: 3.10
Classifier: Programming Language :: Python :: 3.11
Classifier: Programming Language :: Python :: 3.12
License-File: LICENSE
Dynamic: license-file
